labpy/__init__.py
labpy/labpy_rc.py
labpy/labpyworkbench.py
labpy/dev_com/__init__.py
labpy/math_models/__init__.py
labpy/widgets/__init__.py
labpy/widgets/config_widget.py
labpy/widgets/display_alphanumeric_widget.py
labpy/widgets/labpy_test_widget.py
labpy/widgets/temperature_widget.py
labpy/widgets/timer_widget.py
labpy-0.0.4.dist-info/AUTHORS
labpy-0.0.4.dist-info/LICENSE
labpy-0.0.4.dist-info/METADATA
labpy-0.0.4.dist-info/WHEEL
labpy-0.0.4.dist-info/top_level.txt
labpy-0.0.4.dist-info/RECORD
