Metadata-Version: 2.1
Name: labpy
Version: 0.0.4
Summary: labpy - a python laboratory (automation) environment 
Home-page: https://gitlab.com/LARAsuite/pylab
Author: mark doerr
Author-email: mark.doerr@uni-greifswald.de
License: GPLv2+
Keywords: lab automation,Qt5,PySide2,laboratory,instruments,experiments,evaluation,visualisation,serial interface,SiLA2,robots,database
Platform: UNKNOWN
Classifier: License :: OSI Approved :: GNU General Public License v2 or later (GPLv2+)
Classifier: Operating System :: OS Independent
Classifier: Programming Language :: Python
Classifier: Programming Language :: Python :: 3.4
Classifier: Programming Language :: Python :: 3.5
Classifier: Topic :: Utilities
Classifier: Topic :: Scientific/Engineering
Classifier: Topic :: Scientific/Engineering :: Information Analysis
Classifier: Topic :: Scientific/Engineering :: Interface Engine/Protocol Translator
Classifier: Topic :: Scientific/Engineering :: Visualization
Classifier: Topic :: Scientific/Engineering :: Information Analysis
